jsonlt/__init__.py
jsonlt/cli.py
jsonlt/schema_gen.py
jsonlt/xform.py
jsonlt-0.1.0.dist-info/METADATA
jsonlt-0.1.0.dist-info/WHEEL
jsonlt-0.1.0.dist-info/entry_points.txt
jsonlt-0.1.0.dist-info/top_level.txt
jsonlt-0.1.0.dist-info/RECORD
