Metadata-Version: 2.1
Name: jsonlt
Version: 0.1.0
Summary: A JSON transformation library
Home-page: https://github.com/irrelative/jsonlt
Author: Justin Davis
Author-email: jedavis83@gmail.com
Classifier: Programming Language :: Python :: 3
Classifier: License :: OSI Approved :: MIT License
Classifier: Operating System :: OS Independent
Requires-Python: >=3.7
Requires-Dist: pydantic >=2.0.0
